vertica_ml_python/__init__.py
vertica_ml_python/plot.py
vertica_ml_python/toolbox.py
vertica_ml_python/utilities.py
vertica_ml_python/vcolumn.py
vertica_ml_python/vdataframe.py
vertica_ml_python/connections/__init__.py
vertica_ml_python/connections/connect.py
vertica_ml_python/connections/all/__init__.py
vertica_ml_python/learn/__init__.py
vertica_ml_python/learn/cluster.py
vertica_ml_python/learn/datasets.py
vertica_ml_python/learn/decomposition.py
vertica_ml_python/learn/ensemble.py
vertica_ml_python/learn/linear_model.py
vertica_ml_python/learn/metrics.py
vertica_ml_python/learn/model_selection.py
vertica_ml_python/learn/naive_bayes.py
vertica_ml_python/learn/neighbors.py
vertica_ml_python/learn/plot.py
vertica_ml_python/learn/preprocessing.py
vertica_ml_python/learn/svm.py
vertica_ml_python/learn/tree.py
vertica_ml_python/learn/data/__init__.py
vertica_ml_python/learn/data/amazon.csv
vertica_ml_python/learn/data/iris.csv
vertica_ml_python/learn/data/market.csv
vertica_ml_python/learn/data/smart_meters.csv
vertica_ml_python/learn/data/titanic.csv
vertica_ml_python/learn/data/winequality.csv
vertica_ml_python/tests/__init__.py
vertica_ml_python/tests/test_ml.py
vertica_ml_python/tests/test_plot.py
vertica_ml_python/tests/test_preparation_exploration.py
vertica_ml_python-1.0b0.dist-info/LICENSE.txt
vertica_ml_python-1.0b0.dist-info/METADATA
vertica_ml_python-1.0b0.dist-info/WHEEL
vertica_ml_python-1.0b0.dist-info/top_level.txt
vertica_ml_python-1.0b0.dist-info/RECORD
