Metadata-Version: 2.1
Name: vertica-ml-python
Version: 1.0b0
Summary: Vertica-ML-Python simplifies data exploration, data cleaning and machine learning in Vertica.
Home-page: https://github.com/vertica/Vertica-ML-Python
Author: Badr Ouali
Author-email: badr.ouali@microfocus.com
License: UNKNOWN
Keywords: vertica python ml data science machine learning statistics database
Platform: UNKNOWN
Classifier: Intended Audience :: Science/Research
Classifier: Intended Audience :: Developers
Classifier: Programming Language :: Python :: 3
Classifier: Programming Language :: Python :: 3.6
Classifier: Programming Language :: Python :: 3.7
Classifier: Programming Language :: Python :: 3.8
Classifier: Topic :: Database
Classifier: License :: OSI Approved :: Apache Software License
Classifier: Operating System :: OS Independent
Requires-Python: >=3.6
Requires-Dist: matplotlib (>=2.0)
